README.md
setup.py
venafi_vcert_gitlab_integration/download_prev_cert_command.py
venafi_vcert_gitlab_integration/request_certificate_command.py
venafi_vcert_gitlab_integration/utils.py
venafi_vcert_gitlab_integration/version.txt
venafi_vcert_gitlab_integration/version_command.py
venafi_vcert_gitlab_integration.egg-info/PKG-INFO
venafi_vcert_gitlab_integration.egg-info/SOURCES.txt
venafi_vcert_gitlab_integration.egg-info/dependency_links.txt
venafi_vcert_gitlab_integration.egg-info/entry_points.txt
venafi_vcert_gitlab_integration.egg-info/not-zip-safe
venafi_vcert_gitlab_integration.egg-info/requires.txt
venafi_vcert_gitlab_integration.egg-info/top_level.txt