Metadata-Version: 2.1
Name: venafi-vcert-gitlab-integration
Version: 1.1.0
Summary: Venafi Machine Identity Management: Gitlab integration
Home-page: https://github.com/fullstaq-labs/venafi-vcert-gitlab-integration
Author: Fullstaq
Author-email: info@fullstaq.com
License: Apache 2.0
Platform: any
Classifier: Programming Language :: Python :: 3
Classifier: License :: OSI Approved :: Apache Software License
Classifier: Operating System :: OS Independent
Requires-Python: >=3.8
